cgmml/__init__.py
cgmml/analyses/__init__.py
cgmml/analyses/EDA/__init__.py
cgmml/analyses/reliability/__init__.py
cgmml/common/__init__.py
cgmml/common/background_segmentation/__init__.py
cgmml/common/background_segmentation/deeplab/__init__.py
cgmml/common/background_segmentation/deeplab/deeplab.py
cgmml/common/background_segmentation/deeplab/deeplab_model.py
cgmml/common/cgmcore/__init__.py
cgmml/common/cgmcore/datagenerator.py
cgmml/common/cgmcore/etldatagenerator.py
cgmml/common/cgmcore/file_utils.py
cgmml/common/cgmcore/modelutils.py
cgmml/common/cgmcore/pcd_to_pickle.py
cgmml/common/cgmcore/preprocesseddatagenerator.py
cgmml/common/cgmcore/utils.py
cgmml/common/data_utilities/__init__.py
cgmml/common/data_utilities/mlpipeline_utils.py
cgmml/common/data_utilities/rgbd_matching.py
cgmml/common/depthmap_toolkit/__init__.py
cgmml/common/depthmap_toolkit/camera_calibration_lenovo.txt
cgmml/common/depthmap_toolkit/camera_calibration_p30pro_EU.txt
cgmml/common/depthmap_toolkit/constants.py
cgmml/common/depthmap_toolkit/convertdepth2pcd.py
cgmml/common/depthmap_toolkit/convertpcd2depth.py
cgmml/common/depthmap_toolkit/depthmap.py
cgmml/common/depthmap_toolkit/depthmap_utils.py
cgmml/common/depthmap_toolkit/exporter.py
cgmml/common/depthmap_toolkit/toolkit.py
cgmml/common/depthmap_toolkit/visualisation.py
cgmml/common/depthmap_toolkit/tests/huawei_p40pro/camera_calibration.txt
cgmml/common/endpoints/__init__.py
cgmml/common/endpoints/check.py
cgmml/common/endpoints/config_deepensemble_1.py
cgmml/common/endpoints/constants.py
cgmml/common/endpoints/deploy_endpoint.py
cgmml/common/endpoints/entry_script_aci.py
cgmml/common/endpoints/register.py
cgmml/common/evaluation/__init__.py
cgmml/common/evaluation/constants_eval.py
cgmml/common/evaluation/eval_utilities.py
cgmml/common/evaluation/eval_utils.py
cgmml/common/evaluation/evaluation_classes.py
cgmml/common/evaluation/uncertainty_utils.py
cgmml/common/evaluation/CV/csv_utils.py
cgmml/common/evaluation/CV/evaluation.py
cgmml/common/zscore/cgmzscore.egg-info/SOURCES.txt
cgmml/common/zscore/cgmzscore.egg-info/dependency_links.txt
cgmml/common/zscore/cgmzscore.egg-info/top_level.txt
cgm_ml_common-3.1.7.dist-info/LICENSE
cgm_ml_common-3.1.7.dist-info/METADATA
cgm_ml_common-3.1.7.dist-info/WHEEL
cgm_ml_common-3.1.7.dist-info/top_level.txt
cgm_ml_common-3.1.7.dist-info/RECORD
