Metadata-Version: 2.1
Name: cgm-ml-common
Version: 3.1.7
Summary: ChildGrowthMonitor's ML Common code
Home-page: https://github.com/Welthungerhilfe/cgm-ml
Author: Markus Hinsche
Author-email: mhinsche@childgrowthmonitor.com
License: UNKNOWN
Platform: UNKNOWN
Classifier: Intended Audience :: Healthcare Industry
Classifier: Programming Language :: Python
Classifier: Programming Language :: Python :: 3
Classifier: Programming Language :: Python :: 3.6
Classifier: Programming Language :: Python :: 3.7
Classifier: License :: OSI Approved :: GNU General Public License v3 (GPLv3)
Classifier: Operating System :: OS Independent
Requires-Python: >=3.6
